{
    "id": 173,
    "model_input": "[Task Description]\nYou will be given INPUT and INITIAL RESPONSE.\nYou task is to evaluate INITIAL RESPONSE based on the criterion.\nPlease make sure you read and understand these instructions carefully. Please keep this document open while reviewing, and refer to it as needed.\n\n[Criterion]\nKnowledge-Intensiveness (1-5): How much is the INITIAL RESPONSE the level of specialized or domain-specific knowledge required to generate the response. \nA knowledge-intensive initial response should contain enough helpful information in the medical domain, to generate a diagnosis based on the INPUT.\n\n\nFor your information:\nA score of 1 indicates that most of the content in the INITIAL RESPONSE does not contribute to effective medical reasoning. The response might lack depth, relevancy, or demonstrate a superficial understanding of the medical context.\nA score of 5 signifies that the INITIAL RESPONSE contains precise and detailed medical information relevant to the INPUT. The information should be logically structured and clearly demonstrate causality, relevancy, and connections. Even irrelevant or out-of-scope content (if any) should be phrased in a way that the language model can easily discern its lack of utility in the context.\n\n[Evaluation Steps]\n1. Read INPUT and INITIAL RESPONSE carefully.\n2. Rate INITIAL RESPONSE on a scale of 1-5 according to the criterion above.\n3. Provide a brief explanation for your rating.\n4. Always provide your rate after the word PREDICTION:\n\n[Your Task]\nINPUT:\n{'evidences': 'Age: 45\\nSex: F\\nDo you have pain somewhere, related to your reason for consulting?\\n    - N\\nCharacterize your pain:\\n    - haunting\\n    - a knife stroke\\n    - sickening\\nDo you feel pain somewhere?\\n    - upper chest\\n    - epigastric\\nHow intense is the pain?\\n    - 10 (possible values: [0, 1, 2, 3, 4, 5, 6, 7, 8, 9, 10])\\nDoes the pain radiate to another location?\\n    - scapula(R)\\n    - scapula(L)\\nHow precisely is the pain located?\\n    - 4 (possible values: [0, 1, 2, 3, 4, 5, 6, 7, 8, 9, 10])\\nHow fast did the pain appear?\\n    - 8 (possible values: [0, 1, 2, 3, 4, 5, 6, 7, 8, 9, 10])\\nDo you drink alcohol excessively or do you have an addiction to alcohol?\\n    - N\\nAre you feeling nauseous or do you feel like vomiting?\\n    - N\\nHave you traveled out of the country in the last 4 weeks?\\n    - N\\nHave you vomited several times or have you made several efforts to vomit?\\n    - N', 'options': '- Boerhaave\\n- Possible NSTEMI / STEMI\\n- Anaphylaxis\\n- Pancreatic neoplasm\\n- Chagas\\n- Scombroid food poisoning'}\n\nINITIAL RESPONSE:\nLet's think step by step.\n\nThe patient is a 45-year-old female who presents with a haunting, knife-like, and sickening pain in the upper chest and epigastric region, which is intense (rated 10/10) and radiates to the left scapula. The pain is precisely located (rated 4/10) and appeared rapidly (rated 8/10). There is no history of nausea, vomiting, or alcohol addiction.\n\nGiven the patient's symptoms, I would like to rule out life-threatening conditions first. Anaphylaxis is unlikely due to the absence of nausea and vomiting. Chagas disease is a rare condition that is not typically associated with chest pain.\n\nScombroid food poisoning can cause severe chest pain, but it is usually accompanied by other symptoms such as nausea, vomiting, and diarrhea, which are not present in this case.\n\nBoerhaave syndrome is a rare condition that involves a perforation of the esophagus, typically caused by severe vomiting. While it is a possibility, the patient's symptoms do not strongly suggest this diagnosis.\n\nPancreatic neoplasm is a possibility, as the patient's symptoms could be related to pancreatic cancer or pancreatitis. However, the patient's age and the rapid onset of symptoms make a pancreatic neoplasm less likely.\n\nGiven the patient's symptoms, I believe the most likely diagnosis is a Possible NSTEMI (Non-ST Elevation Myocardial Infarction) or STEMI (ST Elevation Myocardial Infarction). The patient's symptoms are consistent with a myocardial infarction, and the rapid onset of symptoms suggests a possible STEMI.\n\n```Possible NSTEMI / STEMI```\n\n[OUTPUT]\nKnowledge-Intensiveness Score:\n",
    "input": {
        "evidences": "Age: 45\nSex: F\nDo you have pain somewhere, related to your reason for consulting?\n    - N\nCharacterize your pain:\n    - haunting\n    - a knife stroke\n    - sickening\nDo you feel pain somewhere?\n    - upper chest\n    - epigastric\nHow intense is the pain?\n    - 10 (possible values: [0, 1, 2, 3, 4, 5, 6, 7, 8, 9, 10])\nDoes the pain radiate to another location?\n    - scapula(R)\n    - scapula(L)\nHow precisely is the pain located?\n    - 4 (possible values: [0, 1, 2, 3, 4, 5, 6, 7, 8, 9, 10])\nHow fast did the pain appear?\n    - 8 (possible values: [0, 1, 2, 3, 4, 5, 6, 7, 8, 9, 10])\nDo you drink alcohol excessively or do you have an addiction to alcohol?\n    - N\nAre you feeling nauseous or do you feel like vomiting?\n    - N\nHave you traveled out of the country in the last 4 weeks?\n    - N\nHave you vomited several times or have you made several efforts to vomit?\n    - N",
        "options": "- Boerhaave\n- Possible NSTEMI / STEMI\n- Anaphylaxis\n- Pancreatic neoplasm\n- Chagas\n- Scombroid food poisoning"
    },
    "label": "Boerhaave",
    "output": {
        "initial_response": "Let's think step by step.\n\nThe patient is a 45-year-old female who presents with a haunting, knife-like, and sickening pain in the upper chest and epigastric region, which is intense (rated 10/10) and radiates to the left scapula. The pain is precisely located (rated 4/10) and appeared rapidly (rated 8/10). There is no history of nausea, vomiting, or alcohol addiction.\n\nGiven the patient's symptoms, I would like to rule out life-threatening conditions first. Anaphylaxis is unlikely due to the absence of nausea and vomiting. Chagas disease is a rare condition that is not typically associated with chest pain.\n\nScombroid food poisoning can cause severe chest pain, but it is usually accompanied by other symptoms such as nausea, vomiting, and diarrhea, which are not present in this case.\n\nBoerhaave syndrome is a rare condition that involves a perforation of the esophagus, typically caused by severe vomiting. While it is a possibility, the patient's symptoms do not strongly suggest this diagnosis.\n\nPancreatic neoplasm is a possibility, as the patient's symptoms could be related to pancreatic cancer or pancreatitis. However, the patient's age and the rapid onset of symptoms make a pancreatic neoplasm less likely.\n\nGiven the patient's symptoms, I believe the most likely diagnosis is a Possible NSTEMI (Non-ST Elevation Myocardial Infarction) or STEMI (ST Elevation Myocardial Infarction). The patient's symptoms are consistent with a myocardial infarction, and the rapid onset of symptoms suggests a possible STEMI.\n\n```Possible NSTEMI / STEMI```",
        "initial_prediction": "Possible NSTEMI / STEMI",
        "initial_cost": 0.0,
        "iteration": [
            {
                "critic_response": "Your reasoning regarding the patient's symptoms and the potential diagnoses is well-structured, but there are a few points to consider:\n\n1. **Pain Characteristics**: The description of the pain as \"haunting,\" \"knife stroke,\" and \"sickening\" is quite evocative and suggests a severe and potentially serious condition. However, the term \"haunting\" is somewhat subjective and may not align with typical medical terminology for pain, which could lead to ambiguity in diagnosis.\n\n2. **Radiation of Pain**: The radiation of pain to both scapulae is significant and can be indicative of cardiac issues, but it can also be seen in other conditions such as gastrointestinal or musculoskeletal problems. This should be taken into account when considering the differential diagnosis.\n\n3. **Exclusion of Other Conditions**: \n   - **Anaphylaxis**: While you correctly ruled this out based on the absence of nausea and vomiting, it is also important to consider other symptoms such as difficulty breathing or swelling, which are not mentioned.\n   - **Boerhaave Syndrome**: Although the absence of vomiting makes this less likely, it is still a condition to consider given the severe chest pain and potential for esophageal perforation.\n   - **Pancreatic Neoplasm**: While the rapid onset of symptoms may make this less likely, pancreatic issues can sometimes present with acute pain, and further investigation may be warranted.\n\n4. **NSTEMI/STEMI Consideration**: Your conclusion that the symptoms are consistent with a myocardial infarction is reasonable, especially given the intensity and nature of the pain. However, it is crucial to consider other risk factors and symptoms that may not have been captured in the initial assessment, such as history of cardiovascular disease, hypertension, or diabetes.\n\n5. **Need for Immediate Evaluation**: Given the severity of the symptoms and the potential for a cardiac event, it would be prudent to recommend immediate medical evaluation, including an ECG and cardiac biomarkers, to confirm or rule out NSTEMI or STEMI.\n\nOverall, your diagnosis of \"Possible NSTEMI / STEMI\" is a strong consideration based on the information provided, but it is essential to remain vigilant for other potential causes and ensure that the patient receives appropriate and timely medical attention. \n\n```STOP```",
                "refiner_response": "-",
                "refiner_prediction": "Possible NSTEMI / STEMI",
                "critic_cost": 0.0009126,
                "refiner_cost": 0
            },
            {
                "critic_response": "-",
                "refiner_response": "-",
                "refiner_prediction": "Possible NSTEMI / STEMI",
                "critic_cost": 0,
                "refiner_cost": 0
            },
            {
                "critic_response": "-",
                "refiner_response": "-",
                "refiner_prediction": "Possible NSTEMI / STEMI",
                "critic_cost": 0,
                "refiner_cost": 0
            }
        ]
    },
    "result": [
        false,
        false,
        false,
        false
    ],
    "prediction": "PREDICTION: 5\n\nThe INITIAL RESPONSE demonstrates a high level of specialized knowledge in the medical domain. The response methodically considers and evaluates each potential diagnosis based on the INPUT symptoms, displaying a clear understanding of medical reasoning. The response also effectively rules out conditions such as Anaphylaxis, Chagas disease, and Boerhaave syndrome by logically assessing the symptoms' relevance and causality. The reasoning for considering a Possible NSTEMI or STEMI as the most likely diagnosis is well-founded, noting the intensity and type of pain, its location, and the rapid onset, aligning these factors with myocardial infarction symptoms. The structured approach and relevant clinical insights provided reflect a deep understanding of the medical context, justifying the high score."
}