{
    "id": 59,
    "model_input": "[Task Description]\nYou will be given INPUT and INITIAL RESPONSE.\nYou task is to evaluate INITIAL RESPONSE based on the criterion.\nPlease make sure you read and understand these instructions carefully. Please keep this document open while reviewing, and refer to it as needed.\n\n[Criterion]\nKnowledge-Intensiveness (1-5): How much is the INITIAL RESPONSE the level of specialized or domain-specific knowledge required to generate the response. \nA knowledge-intensive initial response should contain enough helpful information in the medical domain, to generate a diagnosis based on the INPUT.\n\n\nFor your information:\nA score of 1 indicates that most of the content in the INITIAL RESPONSE does not contribute to effective medical reasoning. The response might lack depth, relevancy, or demonstrate a superficial understanding of the medical context.\nA score of 5 signifies that the INITIAL RESPONSE contains precise and detailed medical information relevant to the INPUT. The information should be logically structured and clearly demonstrate causality, relevancy, and connections. Even irrelevant or out-of-scope content (if any) should be phrased in a way that the language model can easily discern its lack of utility in the context.\n\n[Evaluation Steps]\n1. Read INPUT and INITIAL RESPONSE carefully.\n2. Rate INITIAL RESPONSE on a scale of 1-5 according to the criterion above.\n3. Provide a brief explanation for your rating.\n4. Always provide your rate after the word PREDICTION:\n\n[Your Task]\nINPUT:\n{'evidences': 'Age: 91\\nSex: F\\nAre you currently being treated or have you recently been treated with an oral antibiotic for an ear infection?\\n    - N\\nDo you have pain somewhere, related to your reason for consulting?\\n    - N\\nCharacterize your pain:\\n    - sensitive\\n    - sharp\\nDo you feel pain somewhere?\\n    - ear(R)\\nHow intense is the pain?\\n    - 8 (possible values: [0, 1, 2, 3, 4, 5, 6, 7, 8, 9, 10])\\nDoes the pain radiate to another location?\\n    - nowhere\\nHow precisely is the pain located?\\n    - 6 (possible values: [0, 1, 2, 3, 4, 5, 6, 7, 8, 9, 10])\\nHow fast did the pain appear?\\n    - 4 (possible values: [0, 1, 2, 3, 4, 5, 6, 7, 8, 9, 10])\\nDo you have a fever (either felt or measured with a thermometer)?\\n    - N\\nAre you more irritable or has your mood been very unstable recently?\\n    - N\\nHave you traveled out of the country in the last 4 weeks?\\n    - N\\nAre your vaccinations up to date?\\n    - N', 'options': '- Acute otitis media'}\n\nINITIAL RESPONSE:\n```Acute otitis media is unlikely to be the diagnosis in this patient.```\n\nLet's think step by step. The patient is 91 years old, which is a high-risk age group for developing complications from ear infections. The patient is not experiencing pain, which is unusual for an ear infection. The patient's pain is described as sensitive and sharp, but it is not intense, and it does not radiate to another location. The patient's pain is also not precisely located, which is unusual for an ear infection. The patient's symptoms do not suggest a typical ear infection, and the patient's age and lack of fever or irritability make it less likely that the patient has an acute otitis media.\n\nAdditionally, the patient's vaccination status is not up to date, which increases the risk of developing an ear infection. However, the patient's lack of fever, irritability, and other symptoms make it less likely that the patient has an acute otitis media.\n\nA more likely diagnosis would be a chronic ear condition, such as otosclerosis or presbycusis, which are common in older adults. However, without further information, it is difficult to make a definitive diagnosis.\n\n[OUTPUT]\nKnowledge-Intensiveness Score:\n",
    "input": {
        "evidences": "Age: 91\nSex: F\nAre you currently being treated or have you recently been treated with an oral antibiotic for an ear infection?\n    - N\nDo you have pain somewhere, related to your reason for consulting?\n    - N\nCharacterize your pain:\n    - sensitive\n    - sharp\nDo you feel pain somewhere?\n    - ear(R)\nHow intense is the pain?\n    - 8 (possible values: [0, 1, 2, 3, 4, 5, 6, 7, 8, 9, 10])\nDoes the pain radiate to another location?\n    - nowhere\nHow precisely is the pain located?\n    - 6 (possible values: [0, 1, 2, 3, 4, 5, 6, 7, 8, 9, 10])\nHow fast did the pain appear?\n    - 4 (possible values: [0, 1, 2, 3, 4, 5, 6, 7, 8, 9, 10])\nDo you have a fever (either felt or measured with a thermometer)?\n    - N\nAre you more irritable or has your mood been very unstable recently?\n    - N\nHave you traveled out of the country in the last 4 weeks?\n    - N\nAre your vaccinations up to date?\n    - N",
        "options": "- Acute otitis media"
    },
    "label": "Acute otitis media",
    "output": {
        "initial_response": "```Acute otitis media is unlikely to be the diagnosis in this patient.```\n\nLet's think step by step. The patient is 91 years old, which is a high-risk age group for developing complications from ear infections. The patient is not experiencing pain, which is unusual for an ear infection. The patient's pain is described as sensitive and sharp, but it is not intense, and it does not radiate to another location. The patient's pain is also not precisely located, which is unusual for an ear infection. The patient's symptoms do not suggest a typical ear infection, and the patient's age and lack of fever or irritability make it less likely that the patient has an acute otitis media.\n\nAdditionally, the patient's vaccination status is not up to date, which increases the risk of developing an ear infection. However, the patient's lack of fever, irritability, and other symptoms make it less likely that the patient has an acute otitis media.\n\nA more likely diagnosis would be a chronic ear condition, such as otosclerosis or presbycusis, which are common in older adults. However, without further information, it is difficult to make a definitive diagnosis.",
        "initial_prediction": "Acute otitis media is unlikely to be the diagnosis in this patient.",
        "initial_cost": 0.0,
        "iteration": [
            {
                "critic_response": "Your reasoning regarding the patient's symptoms and the likelihood of acute otitis media is well thought out, but there are a few points that could be reconsidered:\n\n1. **Pain Description**: The patient does report sharp pain in the right ear with an intensity of 8 out of 10. While you mention that the patient is not experiencing pain, the provided information indicates otherwise. This level of pain could indeed suggest an acute process, such as an ear infection.\n\n2. **Radiation and Location of Pain**: The pain is localized to the right ear and does not radiate, which is consistent with acute otitis media. The precision of the pain location (6 out of 10) does not necessarily rule out this diagnosis, as some patients may describe their pain differently.\n\n3. **Fever and Irritability**: The absence of fever and irritability does not definitively exclude acute otitis media, especially in older adults, who may not always present with typical symptoms. Some elderly patients may have atypical presentations of infections.\n\n4. **Vaccination Status**: While the patient's vaccination status is noted as not up to date, this could potentially increase the risk of infections, including otitis media. However, the lack of fever and other systemic symptoms should be weighed carefully.\n\n5. **Chronic Conditions**: While chronic ear conditions like otosclerosis or presbycusis are common in older adults, they typically present with gradual hearing loss rather than acute sharp pain. The acute nature of the pain described here suggests a more immediate issue.\n\nIn summary, while your assessment of the likelihood of acute otitis media is cautious, the presence of significant pain localized to the ear, even in the absence of fever, could still warrant consideration of this diagnosis. Further evaluation, including a physical examination of the ear, would be necessary to confirm or rule out acute otitis media or other potential conditions.",
                "refiner_response": "Let's think step by step. The patient is a 91-year-old female presenting with sharp pain in the right ear, rated as 8 out of 10 in intensity. The pain is localized and does not radiate, which is consistent with conditions affecting the ear. Although the patient does not have fever or irritability, it is important to note that elderly patients may present atypically, and the absence of these symptoms does not definitively rule out an acute ear infection.\n\n1. **Pain Characteristics**: The patient describes the pain as sensitive and sharp, which aligns with acute otitis media, where patients often report significant discomfort.\n\n2. **Location and Intensity**: The pain is localized to the right ear and has a high intensity, which suggests an acute process. The precision of the pain location (6 out of 10) does not negate the possibility of acute otitis media.\n\n3. **Age Considerations**: Given the patient's advanced age, the risk of complications from ear infections is heightened. Older adults may not exhibit classic symptoms, such as fever, making it crucial to consider the diagnosis based on the pain presentation.\n\n4. **Vaccination Status**: The patient's vaccination status being not up to date could increase the risk of infections, including acute otitis media.\n\n5. **Chronic Conditions**: While chronic conditions like otosclerosis or presbycusis are common in older adults, they typically present with gradual hearing loss rather than acute sharp pain, which the patient is experiencing.\n\nConsidering all these factors, the significant pain localized to the ear, despite the absence of fever or irritability, suggests that acute otitis media should still be considered as a potential diagnosis. Further evaluation, including a physical examination of the ear, would be necessary to confirm or rule out this condition.\n\nTherefore, the most likely diagnosis is:\n\n```Acute otitis media```",
                "refiner_prediction": "Acute otitis media",
                "critic_cost": 0.00084735,
                "refiner_cost": 0.0006206999999999999
            },
            {
                "critic_response": "Your reasoning regarding the potential diagnosis of acute otitis media is well-structured, but there are a few points to consider that could refine the assessment:\n\n1. **Pain Characteristics**: While the sharp and sensitive pain in the right ear aligns with acute otitis media, it is important to consider other potential causes of ear pain, such as external ear infections (otitis externa) or referred pain from dental issues or temporomandibular joint disorders.\n\n2. **Absence of Fever**: The lack of fever is notable, especially in an elderly patient. While it is true that older adults may present atypically, the absence of fever could suggest that an acute infection is less likely, or that the body is not mounting a typical inflammatory response.\n\n3. **Precision of Pain Location**: The pain's precision rating of 6 out of 10 indicates some uncertainty in localization, which could suggest that the pain might not be solely due to an ear condition. It may be beneficial to explore other potential sources of pain.\n\n4. **Vaccination Status**: The patient's vaccination status being not up to date could indeed increase the risk of infections, but it would be helpful to know which vaccinations are relevant (e.g., pneumococcal, influenza) and how they relate to the current symptoms.\n\n5. **Need for Further Evaluation**: Given the patient's age and the potential for serious complications from ear infections, a thorough examination, including otoscopic evaluation, is essential to confirm the diagnosis. \n\n6. **Consideration of Other Conditions**: While acute otitis media is a strong consideration, it may be prudent to keep in mind other differential diagnoses that could explain the symptoms, especially in an elderly patient.\n\nOverall, while acute otitis media remains a plausible diagnosis based on the pain characteristics, further evaluation is necessary to confirm this and rule out other potential causes of the ear pain. \n\n```STOP```",
                "refiner_response": "-",
                "refiner_prediction": "Acute otitis media",
                "critic_cost": 0.0008689499999999998,
                "refiner_cost": 0
            },
            {
                "critic_response": "-",
                "refiner_response": "-",
                "refiner_prediction": "Acute otitis media",
                "critic_cost": 0,
                "refiner_cost": 0
            }
        ]
    },
    "result": [
        false,
        true,
        true,
        true
    ],
    "prediction": "PREDICTION: 3\n\nThe INITIAL RESPONSE provides some medical reasoning based on the input, such as considering the patient's age, lack of fever, and type of pain in determining whether acute otitis media is likely. However, there are inaccuracies in interpreting the input, such as stating the patient does not experience pain when it is clearly noted as an intensity of 8, which is quite high. Additionally, the reasoning about vaccination status influencing this type of diagnosis is misplaced as without further context it doesn't conclusively relate to acute otitis media. The response does mention looking into other conditions common in older adults like otosclerosis or presbycusis, but lacks in-depth details that connect the specific symptoms presented here effectively to those conditions. Overall, there is a lack of precise and thorough medical connections, diminishing its effectiveness for knowledgeable diagnoses based on the input information."
}