{
    "id": 226,
    "model_input": "[Task Description]\nYou will be given INPUT and INITIAL RESPONSE.\nYou task is to evaluate INITIAL RESPONSE based on the criterion.\nPlease make sure you read and understand these instructions carefully. Please keep this document open while reviewing, and refer to it as needed.\n\n[Criterion]\nKnowledge-Intensiveness (1-5): How much is the INITIAL RESPONSE the level of specialized or domain-specific knowledge required to generate the response. \nA knowledge-intensive initial response should contain enough helpful information in the medical domain, to generate a diagnosis based on the INPUT.\n\nFor your information:\nA score of 1 indicates that most of the content in the INITIAL RESPONSE does not contribute to effective medical reasoning. The response might lack depth, relevancy, or demonstrate a superficial understanding of the medical context.\nA score of 5 signifies that the INITIAL RESPONSE contains precise and detailed medical information relevant to the INPUT. The information should be logically structured and clearly demonstrate causality, relevancy, and connections. Even irrelevant or out-of-scope content (if any) should be phrased in a way that the language model can easily discern its lack of utility in the context.\n\n[Evaluation Steps]\n1. Read INPUT and INITIAL RESPONSE carefully.\n2. Rate INITIAL RESPONSE on a scale of 1-5 according to the criterion above.\n3. Provide a brief explanation for your rating.\n4. ALWAYS provide the Knowledge-Intensiveness Score after the word PREDICTION:\n\n[Your Task]\nINPUT:\n{'question': 'A 51-year-old man presents for a routine check-up. He has no complaints. At his last annual visit, his physical and laboratory tests were unremarkable. His past medical history is significant for hypercholesterolemia, well managed with rosuvastatin, and hypertension, well managed with hydrochlorothiazide. His current medications also include aspirin. The patient is afebrile, and his vital signs are within normal limits. Physical examination is unremarkable. His laboratory tests are significant for the following:\\nWBC 29,500/mm3\\nHematocrit 26.1%\\nHemoglobin 9.1 g/dL\\nPlatelet count 298,000/mm3\\nA peripheral blood smear and differential shows 92% small normocytic lymphocytes. The patient’s diagnosis in confirmed by bone marrow biopsy and flow cytometry. He is monitored through regular follow-up visits. Three years after the initial diagnosis, the patient presents with swollen cervical and axillary lymph nodes, unintentional weight loss of 4.5 kg (approx. 10 lb), and “rib pain” on his right side. On physical examination, there is palpable, firm, non-tender cervical and axillary lymphadenopathy bilaterally. He also has moderate splenomegaly, which, when palpated, elicits pain. Which of the following is the best treatment for this patient’s most likely diagnosis?', 'options': 'A. Doxorubicinrn\\nB. Bleomycinrn\\nC. Imatinib\\nD. Fludarabinern\\nE. Vincristinern'}\n\nINITIAL RESPONSE:\nBased on the clinical presentation and laboratory findings, this patient likely has chronic lymphocytic leukemia (CLL), which is characterized by an increased number of small, mature lymphocytes in the blood and bone marrow. The symptoms of swollen lymph nodes, weight loss, and splenomegaly suggest progression of the disease.\n\nIn CLL, treatment is typically initiated when the patient exhibits symptoms or evidence of disease progression. The standard treatment options for symptomatic CLL include chemotherapy regimens that often involve purine analogs or combinations of agents.\n\nAmong the options provided, fludarabine is a purine analog that is commonly used in the treatment of CLL, especially in cases where the disease has progressed and the patient is symptomatic.\n\nTherefore, the best treatment for this patient’s most likely diagnosis is:\n\n### Answer\n```D```\n\n[OUTPUT]\nPREDICTION:\n",
    "input": {
        "question": "A 51-year-old man presents for a routine check-up. He has no complaints. At his last annual visit, his physical and laboratory tests were unremarkable. His past medical history is significant for hypercholesterolemia, well managed with rosuvastatin, and hypertension, well managed with hydrochlorothiazide. His current medications also include aspirin. The patient is afebrile, and his vital signs are within normal limits. Physical examination is unremarkable. His laboratory tests are significant for the following:\nWBC 29,500/mm3\nHematocrit 26.1%\nHemoglobin 9.1 g/dL\nPlatelet count 298,000/mm3\nA peripheral blood smear and differential shows 92% small normocytic lymphocytes. The patient’s diagnosis in confirmed by bone marrow biopsy and flow cytometry. He is monitored through regular follow-up visits. Three years after the initial diagnosis, the patient presents with swollen cervical and axillary lymph nodes, unintentional weight loss of 4.5 kg (approx. 10 lb), and “rib pain” on his right side. On physical examination, there is palpable, firm, non-tender cervical and axillary lymphadenopathy bilaterally. He also has moderate splenomegaly, which, when palpated, elicits pain. Which of the following is the best treatment for this patient’s most likely diagnosis?",
        "options": "A. Doxorubicinrn\nB. Bleomycinrn\nC. Imatinib\nD. Fludarabinern\nE. Vincristinern"
    },
    "label": "D",
    "output": {
        "initial_response": "Based on the clinical presentation and laboratory findings, this patient likely has chronic lymphocytic leukemia (CLL), which is characterized by an increased number of small, mature lymphocytes in the blood and bone marrow. The symptoms of swollen lymph nodes, weight loss, and splenomegaly suggest progression of the disease.\n\nIn CLL, treatment is typically initiated when the patient exhibits symptoms or evidence of disease progression. The standard treatment options for symptomatic CLL include chemotherapy regimens that often involve purine analogs or combinations of agents.\n\nAmong the options provided, fludarabine is a purine analog that is commonly used in the treatment of CLL, especially in cases where the disease has progressed and the patient is symptomatic.\n\nTherefore, the best treatment for this patient’s most likely diagnosis is:\n\n### Answer\n```D```",
        "initial_prediction": "D",
        "initial_cost": 0.00025905,
        "iteration": [
            {
                "critic_response": "Your response demonstrates a solid understanding of the clinical presentation and the likely diagnosis of chronic lymphocytic leukemia (CLL). You correctly identify the key features of the patient's condition and the appropriate treatment options. However, there are a few points to consider that could enhance the accuracy of your reasoning:\n\n1. **Diagnosis Confirmation:**\n   - While you have concluded that the patient has CLL based on the laboratory findings and clinical symptoms, it is important to note that the presence of swollen lymph nodes, weight loss, and splenomegaly could also suggest the possibility of transformation to a more aggressive form of the disease, such as Richter's transformation, which is a transformation of CLL into diffuse large B-cell lymphoma (DLBCL). This could influence treatment decisions.\n\n2. **Treatment Considerations:**\n   - Fludarabine is indeed a common treatment for CLL, particularly in cases where the disease is symptomatic. However, it is essential to consider the patient's overall health, any potential comorbidities, and the specific characteristics of the disease (e.g., presence of del(17p) or TP53 mutations) when determining the best treatment approach.\n   - In cases of Richter's transformation, the treatment may differ significantly from standard CLL therapy and could involve more aggressive regimens, including combinations of chemotherapy agents such as R-CHOP (Rituximab, Cyclophosphamide, Doxorubicin, Vincristine, and Prednisone).\n\n3. **Other Options:**\n   - The other options listed (Doxorubicin, Bleomycin, Imatinib, and Vincristine) are not typically first-line treatments for CLL. Doxorubicin and Vincristine are more commonly associated with other types of hematologic malignancies, while Imatinib is primarily used for chronic myeloid leukemia (CML) and certain types of gastrointestinal stromal tumors (GISTs). Bleomycin is used in the treatment of testicular cancer and Hodgkin lymphoma, not CLL.\n\n4. **Monitoring and Follow-Up:**\n   - Given that the patient has a history of CLL and is now presenting with symptoms suggestive of disease progression, it is crucial to ensure that the treatment plan includes regular monitoring and follow-up to assess the response to therapy and adjust as necessary.\n\nIn summary, while your conclusion that fludarabine is the best treatment for this patient’s likely diagnosis of CLL is reasonable, it is essential to consider the possibility of disease transformation and the implications for treatment. A more comprehensive evaluation of the patient's current status and potential treatment options would be beneficial in making the most informed decision. \n\nThis feedback aims to encourage a thorough consideration of the patient's evolving clinical picture and the nuances of treatment in hematologic malignancies.",
                "refiner_response": "Based on the clinical presentation and laboratory findings, this patient is likely diagnosed with chronic lymphocytic leukemia (CLL), characterized by an elevated white blood cell count with a predominance of small, mature lymphocytes, along with symptoms of swollen lymph nodes, weight loss, and splenomegaly. \n\nThe progression of CLL can sometimes lead to more aggressive forms of the disease, such as Richter's transformation, where CLL transforms into diffuse large B-cell lymphoma (DLBCL). This transformation can occur in patients with CLL and is associated with more severe symptoms and a need for more aggressive treatment.\n\nIn terms of treatment options for CLL, fludarabine is indeed a commonly used purine analog, particularly in symptomatic cases. However, if there is suspicion of Richter's transformation, the treatment approach would differ significantly. In such cases, a more aggressive regimen like R-CHOP (Rituximab, Cyclophosphamide, Doxorubicin, Vincristine, and Prednisone) would be more appropriate.\n\nGiven the patient's symptoms of significant lymphadenopathy, weight loss, and splenomegaly, it is crucial to consider the possibility of disease transformation. If the diagnosis is confirmed as Richter's transformation, fludarabine alone would not be sufficient, and a regimen like R-CHOP would be indicated.\n\nAmong the options provided:\n- **A. Doxorubicin**: Part of R-CHOP, used in aggressive lymphomas.\n- **B. Bleomycin**: Not typically used for CLL.\n- **C. Imatinib**: Used for chronic myeloid leukemia (CML), not CLL.\n- **D. Fludarabine**: Used for CLL but may not be sufficient if there is transformation.\n- **E. Vincristine**: Part of combination regimens for aggressive lymphomas.\n\nConsidering the possibility of Richter's transformation and the need for a more aggressive treatment approach, the best treatment for this patient, assuming the diagnosis of transformation to DLBCL, would be a regimen that includes Doxorubicin as part of R-CHOP.\n\nTherefore, the best treatment for this patient’s most likely diagnosis, considering the potential for transformation, is:\n\n### Answer\n```A```",
                "refiner_prediction": "A",
                "critic_cost": 0.0007614,
                "refiner_cost": 0.0009249
            },
            {
                "critic_response": "Your response demonstrates a solid understanding of the clinical scenario and the potential diagnosis of chronic lymphocytic leukemia (CLL) with the possibility of Richter's transformation. However, there are a few areas where your reasoning could be refined:\n\n1. **Diagnosis Confirmation:**\n   - While you correctly identify the patient's symptoms and laboratory findings as indicative of CLL, it is essential to emphasize that the diagnosis of Richter's transformation should be confirmed through appropriate diagnostic imaging or biopsy. The symptoms of swollen lymph nodes, weight loss, and splenomegaly are indeed concerning for transformation, but without confirmation, it is important to avoid assuming that this has occurred.\n\n2. **Treatment Options:**\n   - You mention that fludarabine is commonly used for symptomatic CLL, which is accurate. However, it is also important to note that fludarabine is typically used in earlier stages of CLL or in cases where the disease is not transformed. If Richter's transformation is confirmed, the treatment would indeed shift to a more aggressive regimen, such as R-CHOP, which includes Doxorubicin.\n   - The mention of Doxorubicin as part of R-CHOP is correct, but it would be beneficial to clarify that Doxorubicin alone is not sufficient for treating transformed disease; it must be part of a combination regimen.\n\n3. **Clarification of Options:**\n   - In your analysis of the options, it would be helpful to clarify that while Doxorubicin is part of the R-CHOP regimen, the question asks for the \"best treatment\" among the provided options. If the diagnosis of Richter's transformation is confirmed, the best treatment would be the entire R-CHOP regimen rather than just Doxorubicin alone.\n   - Additionally, while you correctly rule out Imatinib for CLL, it may be worth mentioning that it is specifically indicated for chronic myeloid leukemia (CML) and not applicable in this context.\n\n4. **Consideration of Other Treatments:**\n   - While you focus on Doxorubicin, it might be beneficial to mention that other components of R-CHOP (like Rituximab) are critical for the treatment of DLBCL and should be included in the discussion of the best treatment approach.\n\nIn summary, your reasoning is on the right track, but it would be beneficial to emphasize the need for confirmation of Richter's transformation before concluding on the treatment. Additionally, clarifying that Doxorubicin is part of a combination regimen rather than a standalone treatment would enhance the accuracy of your response. \n\nOverall, your conclusion that Doxorubicin is the best treatment option, assuming the diagnosis of transformation, is reasonable, but it should be framed within the context of the complete R-CHOP regimen for clarity. \n\nThis feedback aims to encourage a more nuanced understanding of the treatment landscape for CLL and its potential transformations.",
                "refiner_response": "Your analysis of the patient's clinical scenario and the potential diagnosis of chronic lymphocytic leukemia (CLL) with the possibility of Richter's transformation is well-articulated. However, let's refine the reasoning and clarify some key points regarding diagnosis confirmation and treatment options.\n\n1. **Diagnosis Confirmation**: \n   - You correctly identify the symptoms and laboratory findings suggestive of CLL. However, it is crucial to confirm the diagnosis of Richter's transformation through appropriate diagnostic imaging or a biopsy of the lymph nodes. The symptoms of swollen lymph nodes, weight loss, and splenomegaly raise suspicion for transformation, but definitive confirmation is necessary before proceeding with treatment decisions.\n\n2. **Treatment Options**:\n   - Fludarabine is indeed a common treatment for symptomatic CLL, particularly in earlier stages. However, if Richter's transformation to diffuse large B-cell lymphoma (DLBCL) is confirmed, the treatment approach would shift significantly. In such cases, a more aggressive regimen like R-CHOP (which includes Doxorubicin, Cyclophosphamide, Vincristine, Prednisone, and Rituximab) would be indicated.\n\n3. **Clarification of Options**:\n   - While Doxorubicin is part of the R-CHOP regimen, the question asks for the \"best treatment\" among the provided options. If Richter's transformation is confirmed, the best treatment would be the entire R-CHOP regimen rather than just Doxorubicin alone. Therefore, while Doxorubicin is a critical component, it should be framed within the context of the complete regimen.\n\n4. **Consideration of Other Treatments**:\n   - It is important to note that Rituximab, which is part of the R-CHOP regimen, plays a significant role in the treatment of DLBCL and should be included in the discussion of the best treatment approach.\n\nGiven these considerations, if we assume that Richter's transformation is confirmed, the best treatment for this patient would indeed be the R-CHOP regimen, which includes Doxorubicin as one of its components. However, since the question specifically asks for the best treatment option from the provided list, and Doxorubicin is the only drug listed that is part of the R-CHOP regimen, it remains the most appropriate choice.\n\n### Final Answer\n```A```",
                "refiner_prediction": "A",
                "critic_cost": 0.00082515,
                "refiner_cost": 0.0009830999999999998
            },
            {
                "critic_response": "Your response provides a solid analysis of the clinical scenario and the potential diagnosis of chronic lymphocytic leukemia (CLL) with the possibility of Richter's transformation. However, there are several important points to clarify and refine regarding the diagnosis and treatment options:\n\n1. **Diagnosis Confirmation**:\n   - You correctly note the symptoms and laboratory findings suggestive of CLL and the potential for Richter's transformation. However, it is essential to emphasize that the diagnosis of Richter's transformation, which indicates a change to a more aggressive form of lymphoma (typically diffuse large B-cell lymphoma), should be confirmed through a biopsy of the lymph nodes or other imaging studies. This confirmation is critical before determining the appropriate treatment.\n\n2. **Treatment Options**:\n   - Fludarabine is indeed a common treatment for CLL, particularly in earlier stages or for patients who are symptomatic. However, if Richter's transformation to DLBCL is confirmed, the treatment approach would typically involve a more aggressive regimen, such as R-CHOP, which includes Doxorubicin, Cyclophosphamide, Vincristine, Prednisone, and Rituximab. This is a key distinction, as the treatment for transformed disease is significantly different from that for standard CLL.\n\n3. **Clarification of Options**:\n   - While Doxorubicin is part of the R-CHOP regimen, the question asks for the \"best treatment\" among the provided options. If Richter's transformation is confirmed, the best treatment would be the entire R-CHOP regimen rather than just Doxorubicin alone. Therefore, while Doxorubicin is a critical component, it should be framed within the context of the complete regimen.\n\n4. **Consideration of Other Treatments**:\n   - It is also important to note that Rituximab, which is part of the R-CHOP regimen, plays a significant role in the treatment of DLBCL and should be included in the discussion of the best treatment approach. The absence of Rituximab in the options provided limits the ability to select the most appropriate treatment.\n\nIn summary, while your conclusion that Doxorubicin is the best treatment option from the provided list is reasonable given its role in the R-CHOP regimen, it is crucial to emphasize the need for confirmation of Richter's transformation and to consider the broader context of treatment for transformed disease. The treatment for Richter's transformation is more complex and typically involves a combination of therapies rather than a single agent.\n\nThis feedback aims to encourage a comprehensive evaluation of the patient's condition and the appropriate treatment options based on the confirmed diagnosis.",
                "refiner_response": "To determine the best treatment for this patient, we need to consider the clinical scenario and the likely diagnosis of chronic lymphocytic leukemia (CLL) with the possibility of Richter's transformation to diffuse large B-cell lymphoma (DLBCL).\n\n1. **Diagnosis Confirmation**: \n   - The patient presents with symptoms such as swollen lymph nodes, unintentional weight loss, and splenomegaly, which raise suspicion for Richter's transformation. This transformation indicates a change to a more aggressive form of lymphoma. It is essential to confirm this diagnosis through a biopsy of the lymph nodes or imaging studies before proceeding with treatment decisions.\n\n2. **Treatment Options**:\n   - If Richter's transformation to DLBCL is confirmed, the treatment approach would typically involve a more aggressive regimen, such as R-CHOP, which includes Doxorubicin, Cyclophosphamide, Vincristine, Prednisone, and Rituximab. This regimen is standard for treating DLBCL and is significantly different from the treatment for standard CLL.\n\n3. **Clarification of Options**:\n   - Among the options provided, Doxorubicin is a key component of the R-CHOP regimen. However, the question asks for the \"best treatment\" among the provided options. If Richter's transformation is confirmed, the best treatment would be the entire R-CHOP regimen rather than just Doxorubicin alone. Therefore, while Doxorubicin is critical, it should be understood within the context of the complete regimen.\n\n4. **Consideration of Other Treatments**:\n   - The absence of Rituximab in the options provided limits the ability to select the most appropriate treatment. Rituximab plays a significant role in the treatment of DLBCL and is an important consideration in the overall treatment strategy.\n\nGiven these considerations, if we assume that Richter's transformation is confirmed, the best treatment for this patient would indeed be the R-CHOP regimen, which includes Doxorubicin as one of its components. However, since the question specifically asks for the best treatment option from the provided list, and Doxorubicin is the only drug listed that is part of the R-CHOP regimen, it remains the most appropriate choice.\n\n### Final Answer\n```A```",
                "refiner_prediction": "A",
                "critic_cost": 0.0007870499999999999,
                "refiner_cost": 0.0009667499999999999
            }
        ]
    },
    "result": [
        true,
        false,
        false,
        false
    ],
    "prediction": "PREDICTION: 5\n\nThe INITIAL RESPONSE displays a high level of knowledge-intensiveness. The response accurately identifies chronic lymphocytic leukemia (CLL) based on the lab results and clinical symptoms, such as an increased number of lymphocytes, swollen lymph nodes, weight loss, and splenomegaly. It then provides a detailed and relevant explanation of the disease's characteristics and treatment protocol, explaining that treatment is initiated upon symptom presentation or disease progression. The response appropriately identifies fludarabine as a suitable treatment, demonstrating clear medical reasoning and understanding of CLL management. Overall, the response is well-structured with precise medical terminology, demonstrating an excellent grasp of the medical context."
}