{
    "id": 71,
    "model_input": "[Task Description]\nYou will be given INPUT and INITIAL RESPONSE.\nYou task is to evaluate INITIAL RESPONSE based on the criterion.\nPlease make sure you read and understand these instructions carefully. Please keep this document open while reviewing, and refer to it as needed.\n\n[Criterion]\nKnowledge-Intensiveness (1-5): How much is the INITIAL RESPONSE the level of specialized or domain-specific knowledge required to generate the response. \nA knowledge-intensive initial response should contain enough helpful information in the medical domain, to generate a diagnosis based on the INPUT.\n\n\nFor your information:\nA score of 1 indicates that most of the content in the INITIAL RESPONSE does not contribute to effective medical reasoning. The response might lack depth, relevancy, or demonstrate a superficial understanding of the medical context.\nA score of 5 signifies that the INITIAL RESPONSE contains precise and detailed medical information relevant to the INPUT. The information should be logically structured and clearly demonstrate causality, relevancy, and connections. Even irrelevant or out-of-scope content (if any) should be phrased in a way that the language model can easily discern its lack of utility in the context.\n\n[Evaluation Steps]\n1. Read INPUT and INITIAL RESPONSE carefully.\n2. Rate INITIAL RESPONSE on a scale of 1-5 according to the criterion above.\n3. Provide a brief explanation for your rating.\n4. Always provide your rate after the word PREDICTION:\n\n[Your Task]\nINPUT:\n{'evidences': 'Age: 10\\nSex: F\\nHave you been in contact with a person with similar symptoms in the past 2 weeks?\\n    - N\\nHave you been coughing up blood?\\n    - N\\nDo you attend or work in a daycare?\\n    - N\\nDo you have pain somewhere, related to your reason for consulting?\\n    - N\\nCharacterize your pain:\\n    - sensitive\\n    - burning\\nDo you feel pain somewhere?\\n    - tonsil(R)\\n    - tonsil(L)\\n    - thyroid cartilage\\n    - palace\\n    - pharynx\\nHow intense is the pain?\\n    - 6 (possible values: [0, 1, 2, 3, 4, 5, 6, 7, 8, 9, 10])\\nDoes the pain radiate to another location?\\n    - nowhere\\nHow precisely is the pain located?\\n    - 4 (possible values: [0, 1, 2, 3, 4, 5, 6, 7, 8, 9, 10])\\nHow fast did the pain appear?\\n    - 5 (possible values: [0, 1, 2, 3, 4, 5, 6, 7, 8, 9, 10])\\nDo you have a fever (either felt or measured with a thermometer)?\\n    - N\\nDo you have a cough?\\n    - N\\nHave you traveled out of the country in the last 4 weeks?\\n    - N\\nAre you immunosuppressed?\\n    - N', 'options': '- Bronchitis\\n- Tuberculosis\\n- Viral pharyngitis\\n- Influenza\\n- Pneumonia'}\n\nINITIAL RESPONSE:\nBased on the patient's symptoms and history, we can start by ruling out some options. The patient does not have a fever, cough, or pain that radiates to another location. They also do not have a history of contact with a person with similar symptoms, attending or working in a daycare, coughing up blood, or being immunosuppressed.\n\nLet's analyze the remaining options:\n\n- Bronchitis: This condition typically presents with cough, which the patient denies having. Additionally, bronchitis is more common in older individuals and smokers.\n\n- Tuberculosis: Tuberculosis usually presents with a chronic cough, night sweats, weight loss, and sometimes blood in the sputum. The patient does not exhibit these symptoms.\n\n- Viral pharyngitis: This condition is characterized by inflammation of the pharynx, often accompanied by pain while swallowing, sore throat, and sometimes fever. The patient reports pain in the tonsil area, pharynx, and a burning sensation, but denies having a fever.\n\n- Influenza: Influenza typically presents with sudden onset of high fever, body aches, and respiratory symptoms such as cough. The patient does not have a fever or cough.\n\n- Pneumonia: Pneumonia usually presents with symptoms such as cough (often productive of phlegm), fever, chest pain, and shortness of breath. The patient does not have these symptoms.\n\nConsidering the patient's age, lack of systemic symptoms,\n\n[OUTPUT]\nKnowledge-Intensiveness Score:\n",
    "input": {
        "evidences": "Age: 10\nSex: F\nHave you been in contact with a person with similar symptoms in the past 2 weeks?\n    - N\nHave you been coughing up blood?\n    - N\nDo you attend or work in a daycare?\n    - N\nDo you have pain somewhere, related to your reason for consulting?\n    - N\nCharacterize your pain:\n    - sensitive\n    - burning\nDo you feel pain somewhere?\n    - tonsil(R)\n    - tonsil(L)\n    - thyroid cartilage\n    - palace\n    - pharynx\nHow intense is the pain?\n    - 6 (possible values: [0, 1, 2, 3, 4, 5, 6, 7, 8, 9, 10])\nDoes the pain radiate to another location?\n    - nowhere\nHow precisely is the pain located?\n    - 4 (possible values: [0, 1, 2, 3, 4, 5, 6, 7, 8, 9, 10])\nHow fast did the pain appear?\n    - 5 (possible values: [0, 1, 2, 3, 4, 5, 6, 7, 8, 9, 10])\nDo you have a fever (either felt or measured with a thermometer)?\n    - N\nDo you have a cough?\n    - N\nHave you traveled out of the country in the last 4 weeks?\n    - N\nAre you immunosuppressed?\n    - N",
        "options": "- Bronchitis\n- Tuberculosis\n- Viral pharyngitis\n- Influenza\n- Pneumonia"
    },
    "label": "Viral pharyngitis",
    "output": {
        "initial_response": "Based on the patient's symptoms and history, we can start by ruling out some options. The patient does not have a fever, cough, or pain that radiates to another location. They also do not have a history of contact with a person with similar symptoms, attending or working in a daycare, coughing up blood, or being immunosuppressed.\n\nLet's analyze the remaining options:\n\n- Bronchitis: This condition typically presents with cough, which the patient denies having. Additionally, bronchitis is more common in older individuals and smokers.\n\n- Tuberculosis: Tuberculosis usually presents with a chronic cough, night sweats, weight loss, and sometimes blood in the sputum. The patient does not exhibit these symptoms.\n\n- Viral pharyngitis: This condition is characterized by inflammation of the pharynx, often accompanied by pain while swallowing, sore throat, and sometimes fever. The patient reports pain in the tonsil area, pharynx, and a burning sensation, but denies having a fever.\n\n- Influenza: Influenza typically presents with sudden onset of high fever, body aches, and respiratory symptoms such as cough. The patient does not have a fever or cough.\n\n- Pneumonia: Pneumonia usually presents with symptoms such as cough (often productive of phlegm), fever, chest pain, and shortness of breath. The patient does not have these symptoms.\n\nConsidering the patient's age, lack of systemic symptoms,",
        "initial_prediction": " the specific symptoms reported, the most likely diagnosis is **Viral pharyngitis**. This aligns with the patient's presentation of pain in the tonsil area and pharynx, along with the absence of fever and cough, which are common in other respiratory conditions.\n\nThus, the final answer is:\n```Viral pharyngitis",
        "initial_cost": 0.0,
        "iteration": [
            {
                "critic_response": "and the specific pain characteristics, the most fitting diagnosis appears to be **Viral pharyngitis**. The presence of sensitive and burning pain in the tonsils and pharynx aligns with the typical presentation of viral pharyngitis, even in the absence of fever. \n\nHowever, there are a few points to consider:\n\n1. **Pain Intensity and Location**: The pain intensity of 6/10 is notable, and while viral pharyngitis can cause discomfort, the level of pain reported may warrant further investigation to rule out other potential causes, such as bacterial infections or other inflammatory conditions.\n\n2. **Absence of Fever**: While viral pharyngitis can occur without fever, the absence of fever and other systemic symptoms could suggest a milder viral infection or a localized issue that may not be fully captured by the options provided.\n\n3. **Other Considerations**: It may be beneficial to consider other potential causes of throat pain, such as allergies, irritants, or even early signs of other infections that may not yet present with full symptoms.\n\n4. **Follow-Up**: Given the patient's age and the nature of the symptoms, a follow-up consultation may be advisable if symptoms persist or worsen, to ensure that no underlying conditions are overlooked.\n\nOverall, while viral pharyngitis is a reasonable conclusion based on the information provided, continued monitoring of the patient's symptoms is important to ensure appropriate care. \n\n```STOP```",
                "refiner_response": "-",
                "refiner_prediction": " the specific symptoms reported, the most likely diagnosis is **Viral pharyngitis**. This aligns with the patient's presentation of pain in the tonsil area and pharynx, along with the absence of fever and cough, which are common in other respiratory conditions.\n\nThus, the final answer is:\n```Viral pharyngitis",
                "critic_cost": 0.0008057999999999999,
                "refiner_cost": 0
            },
            {
                "critic_response": "-",
                "refiner_response": "-",
                "refiner_prediction": " the specific symptoms reported, the most likely diagnosis is **Viral pharyngitis**. This aligns with the patient's presentation of pain in the tonsil area and pharynx, along with the absence of fever and cough, which are common in other respiratory conditions.\n\nThus, the final answer is:\n```Viral pharyngitis",
                "critic_cost": 0,
                "refiner_cost": 0
            },
            {
                "critic_response": "-",
                "refiner_response": "-",
                "refiner_prediction": " the specific symptoms reported, the most likely diagnosis is **Viral pharyngitis**. This aligns with the patient's presentation of pain in the tonsil area and pharynx, along with the absence of fever and cough, which are common in other respiratory conditions.\n\nThus, the final answer is:\n```Viral pharyngitis",
                "critic_cost": 0,
                "refiner_cost": 0
            }
        ]
    },
    "result": [
        false,
        false,
        false,
        false
    ],
    "prediction": "PREDICTION: 4\n\nThe INITIAL RESPONSE demonstrates a substantial level of specialized medical knowledge, providing a detailed analysis of conditions that can be differentiated based on the symptoms provided. The response systematically rules out each condition listed in the options using the patient's symptoms and history. This logical approach reflects a good understanding of the medical context and reasoning required for diagnosis.\n\nHowever, the response could improve its alignment with the task by incorporating more depth in its differential diagnosis process for viral pharyngitis, given it aligns most closely with the patient's symptoms. The response could also be enhanced by discussing the relevance of the age factor in the differential diagnosis and any potential atypical presentations of the conditions considered.\n\nOverall, while the response is thorough and medically sound, there remains room for increased depth and articulation to achieve a perfect score."
}